numpy_cursor.py
numpy_cursor-1.0.5.dist-info/LICENSE
numpy_cursor-1.0.5.dist-info/METADATA
numpy_cursor-1.0.5.dist-info/WHEEL
numpy_cursor-1.0.5.dist-info/top_level.txt
numpy_cursor-1.0.5.dist-info/RECORD
