Metadata-Version: 2.1
Name: numpy-cursor
Version: 1.0.5
Summary: This package contains a Python implementation of a cursor for NumPy matrices. The cursor allows you to conveniently move through a matrix and read or modify its values.
Home-page: https://github.com/NikGariel/NumPy-Cursor
Author: nikgariel
Author-email: nikgariel@yahoo.com
License: UNKNOWN
Keywords: numpy python cursor matrix
Platform: UNKNOWN
Classifier: Programming Language :: Python :: 3.8
Classifier: License :: OSI Approved :: Apache Software License
Classifier: Operating System :: OS Independent
Requires-Python: >=3.8
